shm_ipc_lock/__init__.py
shm_ipc_lock/demo.py
shm_ipc_lock/ipc_lock.py
shm_ipc_lock-0.1.0.dist-info/licenses/LICENCE
shm_ipc_lock-0.1.0.dist-info/METADATA
shm_ipc_lock-0.1.0.dist-info/WHEEL
shm_ipc_lock-0.1.0.dist-info/entry_points.txt
shm_ipc_lock-0.1.0.dist-info/top_level.txt
shm_ipc_lock-0.1.0.dist-info/RECORD
