Metadata-Version: 2.4
Name: shm_ipc_lock
Version: 0.1.0
Summary: Inter-process spinlock using shared memory and compare-and-swap implemented in C for Python.
Author-email: Sergiy Sanin <sanin_sergiy@yahoo.com>
License: MIT
Keywords: ipc,lock,shared-memory,spinlock,atomic,compare-and-swap
Classifier: Programming Language :: Python :: 3
Classifier: Programming Language :: C
Classifier: Operating System :: POSIX :: Linux
Classifier: Topic :: System :: Operating System Kernels
Classifier: Topic :: Software Development :: Libraries
Requires-Python: >=3.8
License-File: LICENCE
Provides-Extra: dev
Requires-Dist: pytest>=7.0; extra == "dev"
Requires-Dist: mypy>=1.0; extra == "dev"
Requires-Dist: black>=24.0; extra == "dev"
Requires-Dist: ruff>=0.6.0; extra == "dev"
Provides-Extra: examples
Requires-Dist: pytest; extra == "examples"
Dynamic: license-file
